chronolog/__init__.py
chronolog/__main__.py
chronolog/chronolog.py
chronolog/cli.py
chronolog/config.py
chronolog/definitions.py
chronolog/api/__init__.py
chronolog/api/api.py
chronolog/api/google.py
chronolog/credentials/google_credentials.json
chronolog_cli-0.1.3.dist-info/LICENSE
chronolog_cli-0.1.3.dist-info/METADATA
chronolog_cli-0.1.3.dist-info/WHEEL
chronolog_cli-0.1.3.dist-info/top_level.txt
chronolog_cli-0.1.3.dist-info/RECORD
